sortdx/__init__.py
sortdx/__main__.py
sortdx/cli.py
sortdx/core.py
sortdx/parsers.py
sortdx/utils.py
sortdx-0.1.1.dist-info/licenses/LICENSE
sortdx-0.1.1.dist-info/METADATA
sortdx-0.1.1.dist-info/WHEEL
sortdx-0.1.1.dist-info/entry_points.txt
sortdx-0.1.1.dist-info/top_level.txt
sortdx-0.1.1.dist-info/RECORD
