Metadata-Version: 2.4
Name: sortdx
Version: 0.1.1
Summary: Universal sorting tool for files, data structures, and large datasets
Author-email: sortdx contributors <dev@sortdx.io>
Maintainer-email: sortdx contributors <dev@sortdx.io>
License: MIT
Project-URL: Homepage, https://github.com/Okymi-X/sortdx
Project-URL: Repository, https://github.com/Okymi-X/sortdx
Project-URL: Issues, https://github.com/Okymi-X/sortdx/issues
Project-URL: Documentation, https://github.com/Okymi-X/sortdx#readme
Keywords: sorting,csv,json,external-sort,cli,data-processing
Classifier: Development Status :: 4 - Beta
Classifier: Intended Audience :: Developers
Classifier: Intended Audience :: Science/Research
Classifier: License :: OSI Approved :: MIT License
Classifier: Operating System :: OS Independent
Classifier: Programming Language :: Python :: 3
Classifier: Programming Language :: Python :: 3.10
Classifier: Programming Language :: Python :: 3.11
Classifier: Programming Language :: Python :: 3.12
Classifier: Programming Language :: Python :: 3.13
Classifier: Topic :: Scientific/Engineering :: Information Analysis
Classifier: Topic :: System :: Archiving :: Compression
Classifier: Topic :: Utilities
Requires-Python: >=3.10
License-File: LICENSE
Provides-Extra: full
Requires-Dist: typer>=0.9.0; extra == "full"
Requires-Dist: rich>=13.0.0; extra == "full"
Requires-Dist: chardet>=5.0.0; extra == "full"
Requires-Dist: python-dateutil>=2.8.0; extra == "full"
Requires-Dist: natsort>=8.0.0; extra == "full"
Provides-Extra: dev
Requires-Dist: pytest>=7.0.0; extra == "dev"
Requires-Dist: pytest-cov>=4.0.0; extra == "dev"
Requires-Dist: black>=23.0.0; extra == "dev"
Requires-Dist: flake8>=6.0.0; extra == "dev"
Requires-Dist: isort>=5.0.0; extra == "dev"
Requires-Dist: mypy>=1.0.0; extra == "dev"
Dynamic: license-file
